[null,{"name":"cos xd","temp":"60","event-type":"3","_id":"ptmGB","actions":[{"token":"","user":"","pass":"","url":"https://api.mcsrvstat.us/1/s29.titanaxe.com:53890","path":"$.players.online","storage":"1","varName":"glace","debugMode":"1","headers":"","name":"Store Json From WebAPI"},{"info":"0","find":"551765638272516096","storage":"1","varName":"kanal","name":"Find Voice Channel"},{"storage":"3","varName":"kanal","toChange":"name","newState":"${tempVars(\"glace\")}","name":"Edit Channel"}]}]